dnf_converter/__init__.py
dnf_converter/__main__.py
dnf_converter/cli.py
dnf_converter/dnf_converter.py
dnf_converter/flask_app.py
dnf_converter/flask_app1.7z
dnf_converter/flask_app/__init__.py
dnf_converter/flask_app/flask_app.py
dnf_converter/flask_app/templates/index.html
dnf_converter/flask_app/upload_files/test.txt
dnf_converter/flask_app/upload_files/test2.txt
dnf_converter/flask_app1/__init__.py
dnf_converter/flask_app1/flask_app.py
dnf_converter/flask_app1/templates/index.html
dnf_converter/flask_app1/upload_files/test.txt
dnf_converter/flask_app1/upload_files/test2.txt
dnf_converter/templates/index.html
dnf_converter/upload_files/test.txt
dnf_converter/upload_files/test2.txt
dnf_converter-0.3.1.dist-info/AUTHORS.rst
dnf_converter-0.3.1.dist-info/LICENSE
dnf_converter-0.3.1.dist-info/METADATA
dnf_converter-0.3.1.dist-info/WHEEL
dnf_converter-0.3.1.dist-info/entry_points.txt
dnf_converter-0.3.1.dist-info/top_level.txt
dnf_converter-0.3.1.dist-info/RECORD
