Metadata-Version: 2.1
Name: dnf-converter
Version: 0.3.1
Summary: An example package. Generated with cookiecutter-pylibrary.
Home-page: https://github.com/christe90/python-dnf_converter
Author: Christian Dressler
Author-email: c.dressler@dressler-christian.de
License: MIT
Project-URL: Documentation, https://python-dnf_converter.readthedocs.io/en/master/
Project-URL: Changelog, https://python-dnf_converter.readthedocs.io/en/latest/changelog.html
Project-URL: Issue Tracker, https://github.com/christe90/python-dnf_converter/issues
Platform: UNKNOWN
Classifier: Development Status :: 5 - Production/Stable
Classifier: Intended Audience :: Developers
Classifier: License :: OSI Approved :: MIT License
Classifier: Operating System :: Unix
Classifier: Operating System :: POSIX
Classifier: Operating System :: Microsoft :: Windows
Classifier: Programming Language :: Python
Classifier: Programming Language :: Python :: 3
Classifier: Programming Language :: Python :: 3 :: Only
Classifier: Programming Language :: Python :: 3.6
Classifier: Programming Language :: Python :: 3.7
Classifier: Programming Language :: Python :: 3.8
Classifier: Programming Language :: Python :: 3.9
Classifier: Programming Language :: Python :: Implementation :: CPython
Classifier: Programming Language :: Python :: Implementation :: PyPy
Classifier: Topic :: Utilities
Requires-Python: >=3.6
